tfdone/__init__.py
tfdone/done.py
tfdone-0.1.2.dist-info/LICENSE
tfdone-0.1.2.dist-info/METADATA
tfdone-0.1.2.dist-info/WHEEL
tfdone-0.1.2.dist-info/top_level.txt
tfdone-0.1.2.dist-info/RECORD
