Metadata-Version: 2.1
Name: tfdone
Version: 0.1.2
Summary: TensorFlow implementation of DONE
Home-page: https://github.com/hosodakazufumi/tfdone
Author: Kazufumi Hosoda
Author-email: hosodakazufumi@gmail.com
License: Apache License 2.0
Platform: UNKNOWN
Classifier: Programming Language :: Python :: 3
Classifier: License :: OSI Approved :: Apache Software License
Classifier: Operating System :: OS Independent
Requires-Python: >=3.7
License-File: LICENSE
